metage2metabo/__init__.py
metage2metabo/__main__.py
metage2metabo/__main_analysis__.py
metage2metabo/sbml_management.py
metage2metabo/utils.py
metage2metabo/m2m/__init__.py
metage2metabo/m2m/community_addedvalue.py
metage2metabo/m2m/community_scope.py
metage2metabo/m2m/individual_scope.py
metage2metabo/m2m/m2m_workflow.py
metage2metabo/m2m/minimal_community.py
metage2metabo/m2m/reconstruction.py
metage2metabo/m2m_analysis/__init__.py
metage2metabo/m2m_analysis/enumeration.py
metage2metabo/m2m_analysis/graph_compression.py
metage2metabo/m2m_analysis/m2m_analysis_workflow.py
metage2metabo/m2m_analysis/solution_graph.py
metage2metabo/m2m_analysis/taxonomy.py
metage2metabo/workflow_data/seeds_workflow.sbml
metage2metabo/workflow_data/workflow_genomes.tar.gz
metage2metabo-1.6.2.dist-info/licenses/LICENSE
metage2metabo-1.6.2.dist-info/METADATA
metage2metabo-1.6.2.dist-info/WHEEL
metage2metabo-1.6.2.dist-info/entry_points.txt
metage2metabo-1.6.2.dist-info/top_level.txt
metage2metabo-1.6.2.dist-info/RECORD
