Metadata-Version: 2.4
Name: Metage2Metabo
Version: 1.6.2
Summary: Automatic reconstruction of draft metabolic networks with Pathway Tools and graph-based metabolic analysis
Author-email: AuReMe <gem-aureme@inria.fr>
License: LGPL-3.0-or-later
Project-URL: Homepage, https://github.com/aureme/metage2metabo
Project-URL: Changelog, https://github.com/aureme/metage2metabo/blob/main/CHANGELOG.md
Requires-Python: >=3.8
License-File: LICENSE
Requires-Dist: miscoto
Requires-Dist: menetools
Requires-Dist: mpwt
Requires-Dist: padmet
Dynamic: license-file
